django_pyodbc_azure-2.0.6.0.dist-info/DESCRIPTION.rst
django_pyodbc_azure-2.0.6.0.dist-info/METADATA
django_pyodbc_azure-2.0.6.0.dist-info/RECORD
django_pyodbc_azure-2.0.6.0.dist-info/WHEEL
django_pyodbc_azure-2.0.6.0.dist-info/metadata.json
django_pyodbc_azure-2.0.6.0.dist-info/top_level.txt
sql_server/__init__.py
sql_server/pyodbc/__init__.py
sql_server/pyodbc/base.py
sql_server/pyodbc/client.py
sql_server/pyodbc/compiler.py
sql_server/pyodbc/creation.py
sql_server/pyodbc/features.py
sql_server/pyodbc/introspection.py
sql_server/pyodbc/operations.py
sql_server/pyodbc/schema.py
