Metadata-Version: 2.0
Name: django-pyodbc-azure
Version: 2.0.6.0
Summary: Django backend for Microsoft SQL Server and Azure SQL Database using pyodbc
Home-page: https://github.com/michiya/django-pyodbc-azure
Author: Michiya Takahashi
Author-email: michiya.takahashi@gmail.com
License: BSD
Keywords: azure django
Platform: UNKNOWN
Classifier: Development Status :: 4 - Beta
Classifier: License :: OSI Approved :: BSD License
Classifier: Framework :: Django
Classifier: Programming Language :: Python
Classifier: Programming Language :: Python :: 3
Classifier: Programming Language :: Python :: 3.4
Classifier: Programming Language :: Python :: 3.5
Classifier: Programming Language :: Python :: 3.6
Classifier: Topic :: Internet :: WWW/HTTP
Requires-Dist: Django (<2.1,>=2.0.6)
Requires-Dist: pyodbc (>=3.0)
